[
 {
    "tableid": 1,
    "state":"free",
    "orders": [
                 {"name":"Anita","price":5},
                 {"name":"Banshee","price":5},
                 {"name":"Bitter Sweet","price":3.5}
             ]
 },
 {
 "tableid": 2,
 "state":"free",
 "orders": [
          {"name":"Abbey","price":5},
          {"name":"Alexander","price":5},
          {"name":"Americano","price":3.5}
          ]
 },
 {
 "tableid": 3,
 "state":"busy",
 "sum":18.00,
 "person":3,
 "orders": [
          {"name":"Torta alla frutta","price":4},
          {"name":"Torta della nonna","price":4},
          {"name":"Pasticci misti","price":11}
          ]
 },
 {
 "tableid": 4,
 "state":"free",
 "orders": [
          {"name":"Torta alla frutta","price":4},
          {"name":"Torta della nonna","price":4},
          {"name":"Pasticci misti","price":11}
          ]
 },
 {
 "tableid": 5,
 "state":"free",
 "orders": [
          {"name":"Torta alla frutta","price":4},
          {"name":"Torta della nonna","price":4},
          {"name":"Pasticci misti","price":11}
          ]
 },
 {
 "tableid": 6,
 "state":"free",
 "orders": [
          {"name":"Torta alla frutta","price":4},
          {"name":"Torta della nonna","price":4},
          {"name":"Pasticci misti","price":11}
          ]
 },
 {
 "tableid": 7,
 "state":"busy",
 "sum":25.00,
 "person":2,
 "orders": [
          {"name":"Torta alla frutta","price":4},
          {"name":"Torta della nonna","price":4},
          {"name":"Pasticci misti","price":11}
          ]
 },
 {
 "tableid": 8,
 "state":"free",
 "orders": [
          {"name":"Torta alla frutta","price":4},
          {"name":"Torta della nonna","price":4},
          {"name":"Pasticci misti","price":11}
          ]
 }
]
